odoo/addons/account_payment_term_discount/README.rst
odoo/addons/account_payment_term_discount/__init__.py
odoo/addons/account_payment_term_discount/__manifest__.py
odoo/addons/account_payment_term_discount/changes.txt
odoo/addons/account_payment_term_discount/i18n/account_cash_discount_61.pot
odoo/addons/account_payment_term_discount/i18n/account_payment_term_discount.pot
odoo/addons/account_payment_term_discount/i18n/de.po
odoo/addons/account_payment_term_discount/i18n/es_AR.po
odoo/addons/account_payment_term_discount/i18n/fr_FR.po
odoo/addons/account_payment_term_discount/models/__init__.py
odoo/addons/account_payment_term_discount/models/account_move.py
odoo/addons/account_payment_term_discount/models/account_payment_term.py
odoo/addons/account_payment_term_discount/models/product_template.py
odoo/addons/account_payment_term_discount/readme/CONFIGURE.rst
odoo/addons/account_payment_term_discount/readme/CONTRIBUTORS.rst
odoo/addons/account_payment_term_discount/readme/CREDITS.rst
odoo/addons/account_payment_term_discount/readme/DESCRIPTION.rst
odoo/addons/account_payment_term_discount/readme/USAGE.rst
odoo/addons/account_payment_term_discount/security/ir.model.access.csv
odoo/addons/account_payment_term_discount/static/description/icon.png
odoo/addons/account_payment_term_discount/static/description/index.html
odoo/addons/account_payment_term_discount/tests/__init__.py
odoo/addons/account_payment_term_discount/tests/test_customer_payment_term.py
odoo/addons/account_payment_term_discount/views/account_move_view.xml
odoo/addons/account_payment_term_discount/views/account_payment_term_view.xml
odoo/addons/account_payment_term_discount/views/product_view.xml
odoo/addons/account_payment_term_discount/wizard/__init__.py
odoo/addons/account_payment_term_discount/wizard/account_payment_register.py
odoo/addons/account_payment_term_discount/wizard/account_payment_register.xml
odoo14_addon_account_payment_term_discount-14.0.1.1.7.dist-info/METADATA
odoo14_addon_account_payment_term_discount-14.0.1.1.7.dist-info/WHEEL
odoo14_addon_account_payment_term_discount-14.0.1.1.7.dist-info/top_level.txt
odoo14_addon_account_payment_term_discount-14.0.1.1.7.dist-info/RECORD
